CHANGELOG.rst
MANIFEST.in
README.rst
setup.py
django_tinymce_4.egg-info/PKG-INFO
django_tinymce_4.egg-info/SOURCES.txt
django_tinymce_4.egg-info/dependency_links.txt
django_tinymce_4.egg-info/not-zip-safe
django_tinymce_4.egg-info/requires.txt
django_tinymce_4.egg-info/top_level.txt
tinymce_4/__init__.py
tinymce_4/fields.py
tinymce_4/widgets.py
tinymce_4/static/.DS_Store
tinymce_4/static/filebrowser/js/FB_TinyMCE.js
tinymce_4/static/grappelli/tinymce/jscripts/tiny_mce/tiny_mce_popup.js
tinymce_4/static/tinymce_4/.DS_Store
tinymce_4/static/tinymce_4/css/.DS_Store
tinymce_4/static/tinymce_4/css/__tinymce-4.css
tinymce_4/static/tinymce_4/css/__tinymce-4.css.map
tinymce_4/static/tinymce_4/css/list.css
tinymce_4/static/tinymce_4/css/main.css
tinymce_4/static/tinymce_4/css/reset.css
tinymce_4/static/tinymce_4/css/settings.css
tinymce_4/static/tinymce_4/css/styles.css
tinymce_4/static/tinymce_4/css/table.css
tinymce_4/static/tinymce_4/css/text.css
tinymce_4/static/tinymce_4/css/title.css
tinymce_4/static/tinymce_4/langs/ru.js
tinymce_4/static/tinymce_4/plugins/insertZoomImage.js
tinymce_4/static/tinymce_4/plugins/typograf.js
tinymce_4/static/tinymce_4/settings/django-filebrowser.js
tinymce_4/static/tinymce_4/settings/django-grapelli.css
tinymce_4/static/tinymce_4/settings/full.js
tinymce_4/static/tinymce_4/settings/small.js
tinymce_4/static/tinymce_4/settings/tinymce_initialization.js
tinymce_4/static/tinymce_4/settings/full/custom_style_formats.js
tinymce_4/static/tinymce_4/settings/full/external_plugins.js
tinymce_4/static/tinymce_4/settings/full/image_class_list.js
tinymce_4/static/tinymce_4/settings/full/language.js
tinymce_4/static/tinymce_4/settings/full/menu.js
tinymce_4/static/tinymce_4/settings/full/menubar.js
tinymce_4/static/tinymce_4/settings/full/plugins.js
tinymce_4/static/tinymce_4/settings/full/settings.js
tinymce_4/static/tinymce_4/settings/full/setup.js
tinymce_4/static/tinymce_4/settings/full/style_formats.js
tinymce_4/static/tinymce_4/settings/full/table_class_list.js
tinymce_4/static/tinymce_4/settings/full/templates.js
tinymce_4/static/tinymce_4/settings/full/toolbar.js
tinymce_4/static/tinymce_4/tinymce/.bower.json
tinymce_4/static/tinymce_4/tinymce/bower.json
