Metadata-Version: 1.1
Name: django-tinymce-4
Version: 0.0.27
Summary: Integrate TinyMCE 4 in Django projects
Home-page: https://github.com/ITCase-django/django-tinymce-4
Author: Petr Zelenin, Arkadiy Zamaraev, Nikita Shalakov
Author-email: po.zelenin@itcase.pro, arkadiy@bk.ru, ggift@mail.ru
License: MIT
Platform: UNKNOWN
Classifier: Development Status :: 5 - Production/Stable
Classifier: Environment :: Web Environment
Classifier: Framework :: Django
Classifier: Intended Audience :: Developers
Classifier: License :: OSI Approved :: MIT License
Classifier: Natural Language :: English
Classifier: Operating System :: OS Independent
Classifier: Programming Language :: Python
Classifier: Programming Language :: Python :: 3.4
Classifier: Programming Language :: Python :: 3.5
Classifier: Programming Language :: Python :: 3.6
Classifier: Programming Language :: JavaScript
Classifier: Framework :: Django
Classifier: Framework :: Django :: 1.9
Classifier: Framework :: Django :: 1.10
Classifier: Framework :: Django :: 1.11
Classifier: Topic :: Software Development :: Libraries :: Application Frameworks
Classifier: Topic :: Software Development :: Libraries :: Python Modules
